lona_picocss/__init__.py
lona_picocss/apps.py
lona_picocss/color_schemes.py
lona_picocss/middlewares.py
lona_picocss/navigation.py
lona_picocss/routes.py
lona_picocss/settings.py
lona_picocss/utils.py
lona_picocss/html/__init__.py
lona_picocss/html/base.py
lona_picocss/html/buttons.py
lona_picocss/html/cards.py
lona_picocss/html/generic.py
lona_picocss/html/icons.py
lona_picocss/html/inputs.py
lona_picocss/html/links.py
lona_picocss/html/modal.py
lona_picocss/html/progress.py
lona_picocss/html/scroller.py
lona_picocss/html/tabs.py
lona_picocss/static/lona-picocss/feather-widgets.js
lona_picocss/static/lona-picocss/logo.svg
lona_picocss/static/lona-picocss/lona-picocss.css
lona_picocss/static/lona-picocss/picocss-widgets.js
lona_picocss/static/lona-picocss/dist/feather-icons/LICENSE
lona_picocss/static/lona-picocss/dist/feather-icons/feather-sprite.svg
lona_picocss/static/lona-picocss/dist/feather-icons/feather.js
lona_picocss/static/lona-picocss/dist/feather-icons/feather.js.map
lona_picocss/static/lona-picocss/dist/feather-icons/feather.min.js
lona_picocss/static/lona-picocss/dist/feather-icons/feather.min.js.map
lona_picocss/static/lona-picocss/dist/feather-icons/icons.json
lona_picocss/static/lona-picocss/dist/pico/LICENSE.md
lona_picocss/static/lona-picocss/dist/pico/css/pico.classless.css
lona_picocss/static/lona-picocss/dist/pico/css/pico.classless.css.map
lona_picocss/static/lona-picocss/dist/pico/css/pico.classless.min.css
lona_picocss/static/lona-picocss/dist/pico/css/pico.classless.min.css.map
lona_picocss/static/lona-picocss/dist/pico/css/pico.css
lona_picocss/static/lona-picocss/dist/pico/css/pico.css.map
lona_picocss/static/lona-picocss/dist/pico/css/pico.fluid.classless.css
lona_picocss/static/lona-picocss/dist/pico/css/pico.fluid.classless.css.map
lona_picocss/static/lona-picocss/dist/pico/css/pico.fluid.classless.min.css
lona_picocss/static/lona-picocss/dist/pico/css/pico.fluid.classless.min.css.map
lona_picocss-0.4.4.dist-info/LICENSE.txt
lona_picocss-0.4.4.dist-info/METADATA
lona_picocss-0.4.4.dist-info/WHEEL
lona_picocss-0.4.4.dist-info/top_level.txt
lona_picocss-0.4.4.dist-info/RECORD
