Metadata-Version: 2.1
Name: lona-picocss
Version: 0.4.4
Summary: Pico.css bindings for Lona
Author-email: Florian Scherf <mail@florianscherf.de>
License: MIT License
Project-URL: Homepage, https://github.com/lona-web-org/lona-picocss
Project-URL: Repository, https://github.com/lona-web-org/lona-picocss
Project-URL: Bug Tracker, https://github.com/lona-web-org/lona-picocss/issues
Classifier: Development Status :: 4 - Beta
Classifier: License :: OSI Approved :: MIT License
Classifier: Natural Language :: English
Classifier: Programming Language :: Python :: 3 :: Only
Classifier: Topic :: Internet :: WWW/HTTP
Classifier: Topic :: Internet :: WWW/HTTP :: Dynamic Content
Requires-Python: >=3.7
License-File: LICENSE.txt
Requires-Dist: lona >=1.12.1
Provides-Extra: packaging
Requires-Dist: build ; extra == 'packaging'
Requires-Dist: twine ; extra == 'packaging'
Provides-Extra: test
Requires-Dist: tox ; extra == 'test'
Requires-Dist: coverage ==7.1.0 ; extra == 'test'
Requires-Dist: pytest ==7.2.1 ; extra == 'test'
Requires-Dist: pytest-aiohttp ==1.0.4 ; extra == 'test'
Requires-Dist: pytest-django ==4.5.2 ; extra == 'test'
Requires-Dist: playwright ==1.34.0 ; extra == 'test'
Requires-Dist: lona-django ==0.1.1 ; extra == 'test'
Requires-Dist: aiohttp-wsgi ==0.10.0 ; extra == 'test'
Requires-Dist: django <3.3,>=3.2 ; extra == 'test'
